main.py
shodan_mcp-0.1.0.dist-info/METADATA
shodan_mcp-0.1.0.dist-info/WHEEL
shodan_mcp-0.1.0.dist-info/entry_points.txt
shodan_mcp-0.1.0.dist-info/top_level.txt
shodan_mcp-0.1.0.dist-info/RECORD
