Metadata-Version: 2.4
Name: shodan-mcp
Version: 0.1.0
Summary: A Model Context Protocol (MCP) toolkit for Shodan API integration.
Author: Jak Bin
Classifier: Programming Language :: Python :: 3
Classifier: License :: OSI Approved :: MIT License
Classifier: Operating System :: OS Independent
Requires-Python: >=3.7
Requires-Dist: shodan
Requires-Dist: mcp
Dynamic: author
Dynamic: classifier
Dynamic: requires-dist
Dynamic: requires-python
Dynamic: summary
